irus_uk_driver/__init__.py
irus_uk_driver/client.py
irus_uk_driver/serializers.py
hirmeos_irus_uk_driver-0.0.2.dist-info/LICENSE
hirmeos_irus_uk_driver-0.0.2.dist-info/METADATA
hirmeos_irus_uk_driver-0.0.2.dist-info/WHEEL
hirmeos_irus_uk_driver-0.0.2.dist-info/top_level.txt
hirmeos_irus_uk_driver-0.0.2.dist-info/RECORD
